nb_time/__init__.py
nb_time-2.8.dist-info/METADATA
nb_time-2.8.dist-info/WHEEL
nb_time-2.8.dist-info/top_level.txt
nb_time-2.8.dist-info/RECORD
